fast_package_file/__init__.py
fast_package_file-1.1.dist-info/LICENSE
fast_package_file-1.1.dist-info/METADATA
fast_package_file-1.1.dist-info/WHEEL
fast_package_file-1.1.dist-info/top_level.txt
fast_package_file-1.1.dist-info/RECORD
