Metadata-Version: 2.1
Name: fast-package-file
Version: 1.1
Summary: Package a directory to a file, with fast file access and compression support
Home-page: https://github.com/Kataiser/fast-package-file
Author: Kataiser
Author-email: mecharon1.gm@gmail.com
License: UNKNOWN
Platform: UNKNOWN
Classifier: Programming Language :: Python :: 3
Classifier: License :: OSI Approved :: MIT License
Classifier: Operating System :: OS Independent
Classifier: Intended Audience :: Developers
Classifier: Natural Language :: English
Classifier: Programming Language :: Python :: 3.5
Classifier: Programming Language :: Python :: 3.6
Classifier: Programming Language :: Python :: 3.7
